zenhub/__init__.py
zenhub/_version.py
zenhub/exceptions.py
zenhub/models.py
zenhub/types.py
zenhub/utils.py
zenhub/core/__init__.py
zenhub/core/base.py
zenhub/core/dependencies.py
zenhub/core/epics.py
zenhub/core/issues.py
zenhub/core/milestones.py
zenhub/core/rate.py
zenhub/core/release_report_issues.py
zenhub/core/release_reports.py
zenhub/core/workspaces.py
pyzenhub-0.3.2.dist-info/LICENSE.txt
pyzenhub-0.3.2.dist-info/METADATA
pyzenhub-0.3.2.dist-info/WHEEL
pyzenhub-0.3.2.dist-info/top_level.txt
pyzenhub-0.3.2.dist-info/RECORD
