Metadata-Version: 2.1
Name: pyzenhub
Version: 0.3.2
Summary: Python bindings to the Zenhub API
Home-page: https://github.com/goanpeca/pyzenhub
Author: Gonzalo Pena-Castellanos
Author-email: goanpeca@gmail.com
License: MIT
Project-URL: Source, https://github.com/goanpeca/pyzenhub
Project-URL: Tracker, https://github.com/goanpeca/pyzenhub/issues
Project-URL: Changelog, https://github.com/goanpeca/pyzenhub/blob/main/CHANGELOG.md
Keywords: zenhub,api
Classifier: Development Status :: 5 - Production/Stable
Classifier: Intended Audience :: Developers
Classifier: License :: OSI Approved :: MIT License
Classifier: Operating System :: OS Independent
Classifier: Programming Language :: Python
Classifier: Programming Language :: Python :: 3
Classifier: Programming Language :: Python :: 3 :: Only
Classifier: Programming Language :: Python :: 3.8
Classifier: Programming Language :: Python :: 3.9
Classifier: Programming Language :: Python :: 3.10
Classifier: Programming Language :: Python :: Implementation :: CPython
Requires-Python: >=3.8
License-File: LICENSE.txt
Requires-Dist: packaging
Requires-Dist: pydantic (<2)
Requires-Dist: requests
Requires-Dist: types-requests
Requires-Dist: typing-extensions
